pyinfra/__init__.py
pyinfra/__main__.py
pyinfra/context.py
pyinfra/local.py
pyinfra/progress.py
pyinfra/py.typed
pyinfra/version.py
pyinfra/api/__init__.py
pyinfra/api/arguments.py
pyinfra/api/arguments_typed.py
pyinfra/api/command.py
pyinfra/api/config.py
pyinfra/api/connect.py
pyinfra/api/connectors.py
pyinfra/api/deploy.py
pyinfra/api/exceptions.py
pyinfra/api/facts.py
pyinfra/api/host.py
pyinfra/api/inventory.py
pyinfra/api/operation.py
pyinfra/api/operations.py
pyinfra/api/state.py
pyinfra/api/util.py
pyinfra/connectors/__init__.py
pyinfra/connectors/base.py
pyinfra/connectors/chroot.py
pyinfra/connectors/docker.py
pyinfra/connectors/dockerssh.py
pyinfra/connectors/local.py
pyinfra/connectors/ssh.py
pyinfra/connectors/ssh_util.py
pyinfra/connectors/terraform.py
pyinfra/connectors/util.py
pyinfra/connectors/vagrant.py
pyinfra/connectors/sshuserclient/__init__.py
pyinfra/connectors/sshuserclient/client.py
pyinfra/connectors/sshuserclient/config.py
pyinfra/facts/__init__.py
pyinfra/facts/apk.py
pyinfra/facts/apt.py
pyinfra/facts/brew.py
pyinfra/facts/bsdinit.py
pyinfra/facts/cargo.py
pyinfra/facts/choco.py
pyinfra/facts/deb.py
pyinfra/facts/dnf.py
pyinfra/facts/docker.py
pyinfra/facts/files.py
pyinfra/facts/gem.py
pyinfra/facts/git.py
pyinfra/facts/gpg.py
pyinfra/facts/hardware.py
pyinfra/facts/iptables.py
pyinfra/facts/launchd.py
pyinfra/facts/lxd.py
pyinfra/facts/mysql.py
pyinfra/facts/npm.py
pyinfra/facts/openrc.py
pyinfra/facts/pacman.py
pyinfra/facts/pip.py
pyinfra/facts/pkg.py
pyinfra/facts/pkgin.py
pyinfra/facts/postgres.py
pyinfra/facts/postgresql.py
pyinfra/facts/rpm.py
pyinfra/facts/selinux.py
pyinfra/facts/server.py
pyinfra/facts/snap.py
pyinfra/facts/systemd.py
pyinfra/facts/sysvinit.py
pyinfra/facts/upstart.py
pyinfra/facts/vzctl.py
pyinfra/facts/xbps.py
pyinfra/facts/yum.py
pyinfra/facts/zypper.py
pyinfra/facts/util/__init__.py
pyinfra/facts/util/databases.py
pyinfra/facts/util/packaging.py
pyinfra/facts/util/win_files.py
pyinfra_forked_by_stone_w4tch3r-0.3.3.dist-info/LICENSE.md
pyinfra_forked_by_stone_w4tch3r-0.3.3.dist-info/METADATA
pyinfra_forked_by_stone_w4tch3r-0.3.3.dist-info/WHEEL
pyinfra_forked_by_stone_w4tch3r-0.3.3.dist-info/entry_points.txt
pyinfra_forked_by_stone_w4tch3r-0.3.3.dist-info/top_level.txt
pyinfra_forked_by_stone_w4tch3r-0.3.3.dist-info/RECORD
