Metadata-Version: 2.1
Name: pyinfra_forked_by_stone-w4tch3r
Version: 0.3.3
Summary: Custom version for developing pyinfra
Home-page: https://pyinfra.com
Author: stone-w4tch3r
Author-email: 100294019+stone-w4tch3r@users.noreply.github.com
License: MIT
Project-URL: Documentation, https://docs.pyinfra.com
Project-URL: GitHub, https://github.com/stone-w4tch3r/pyinfra_fork
Classifier: Development Status :: 5 - Production/Stable
Classifier: Environment :: Console
Classifier: Intended Audience :: Developers
Classifier: Intended Audience :: System Administrators
Classifier: Intended Audience :: Information Technology
Classifier: License :: OSI Approved :: MIT License
Classifier: Operating System :: OS Independent
Classifier: Programming Language :: Python :: 3
Classifier: Programming Language :: Python :: 3.7
Classifier: Programming Language :: Python :: 3.8
Classifier: Programming Language :: Python :: 3.9
Classifier: Programming Language :: Python :: 3.10
Classifier: Topic :: System :: Systems Administration
Classifier: Topic :: System :: Installation/Setup
Classifier: Topic :: Utilities
License-File: LICENSE.md
Requires-Dist: gevent >=1.5
Requires-Dist: paramiko <4,>=2.7
Requires-Dist: click >2
Requires-Dist: jinja2 <4,>2
Requires-Dist: python-dateutil <3,>2
Requires-Dist: setuptools
Requires-Dist: configparser
Requires-Dist: pywinrm
Requires-Dist: typeguard
Requires-Dist: distro <2,>=1.6
Requires-Dist: typing-extensions ; python_version < "3.11"
Requires-Dist: graphlib-backport ; python_version < "3.9"
Provides-Extra: dev
Requires-Dist: pytest ==7.2.0 ; extra == 'dev'
Requires-Dist: coverage ==6.5 ; extra == 'dev'
Requires-Dist: pytest-cov ==4.0.0 ; extra == 'dev'
Requires-Dist: black ==22.3.0 ; extra == 'dev'
Requires-Dist: isort ==5.10.1 ; extra == 'dev'
Requires-Dist: flake8 ==4.0.1 ; extra == 'dev'
Requires-Dist: flake8-black ==0.3.0 ; extra == 'dev'
Requires-Dist: flake8-isort ==4.1.1 ; extra == 'dev'
Requires-Dist: mypy ; extra == 'dev'
Requires-Dist: types-cryptography ; extra == 'dev'
Requires-Dist: types-paramiko ; extra == 'dev'
Requires-Dist: types-python-dateutil ; extra == 'dev'
Requires-Dist: types-PyYAML ; extra == 'dev'
Requires-Dist: types-setuptools ; extra == 'dev'
Requires-Dist: pyinfra-guzzle-sphinx-theme ==0.15 ; extra == 'dev'
Requires-Dist: myst-parser ==2.0.0 ; extra == 'dev'
Requires-Dist: sphinx ==6.2.1 ; extra == 'dev'
Requires-Dist: wheel ; extra == 'dev'
Requires-Dist: twine ; extra == 'dev'
Requires-Dist: ipython ; extra == 'dev'
Requires-Dist: ipdb ; extra == 'dev'
Requires-Dist: ipdbplugin ; extra == 'dev'
Requires-Dist: flake8-spellcheck ==0.12.1 ; extra == 'dev'
Requires-Dist: redbaron ; extra == 'dev'
Provides-Extra: docs
Requires-Dist: pyinfra-guzzle-sphinx-theme ==0.15 ; extra == 'docs'
Requires-Dist: myst-parser ==2.0.0 ; extra == 'docs'
Requires-Dist: sphinx ==6.2.1 ; extra == 'docs'
Provides-Extra: test
Requires-Dist: pytest ==7.2.0 ; extra == 'test'
Requires-Dist: coverage ==6.5 ; extra == 'test'
Requires-Dist: pytest-cov ==4.0.0 ; extra == 'test'
Requires-Dist: black ==22.3.0 ; extra == 'test'
Requires-Dist: isort ==5.10.1 ; extra == 'test'
Requires-Dist: flake8 ==4.0.1 ; extra == 'test'
Requires-Dist: flake8-black ==0.3.0 ; extra == 'test'
Requires-Dist: flake8-isort ==4.1.1 ; extra == 'test'
Requires-Dist: mypy ; extra == 'test'
Requires-Dist: types-cryptography ; extra == 'test'
Requires-Dist: types-paramiko ; extra == 'test'
Requires-Dist: types-python-dateutil ; extra == 'test'
Requires-Dist: types-PyYAML ; extra == 'test'
Requires-Dist: types-setuptools ; extra == 'test'
